DILPREET1910_Mediapipe/HandTrackingModule.py
DILPREET1910_Mediapipe/__init__.py
DILPREET1910_Mediapipe-0.1.1.dist-info/LICENSE
DILPREET1910_Mediapipe-0.1.1.dist-info/METADATA
DILPREET1910_Mediapipe-0.1.1.dist-info/WHEEL
DILPREET1910_Mediapipe-0.1.1.dist-info/top_level.txt
DILPREET1910_Mediapipe-0.1.1.dist-info/RECORD
