Metadata-Version: 2.1
Name: DILPREET1910-Mediapipe
Version: 0.1.1
Summary: a minimalist custom module for mediapipe
Home-page: https://github.com/DILPREET1910/DILPREET1910_Mediapipe
Author: DILPREET1910
Author-email: dsahney1910@gmail.com
Project-URL: Bug Tracker, https://github.com/DILPREET1910/DILPREET1910_Mediapipe/issues
Classifier: Programming Language :: Python :: 3.10
Classifier: Operating System :: OS Independent
Requires-Python: >=3.6
License-File: LICENSE
